neuralfit/__init__.py
neuralfit/__init__.pyi
neuralfit/neuralfit.cp37-win_amd64.pyd
neuralfit/optimizers/__init__.pyi
neuralfit-0.2.2.dist-info/METADATA
neuralfit-0.2.2.dist-info/WHEEL
neuralfit-0.2.2.dist-info/top_level.txt
neuralfit-0.2.2.dist-info/RECORD
