Metadata-Version: 2.1
Name: neuralfit
Version: 0.2.2
Summary: A neuro-evolution package.
Home-page: https://neuralfit.net/
Author: NeuralFit
Author-email: info@neuralfit.net
License: https://neuralfit.net/terms-and-conditions/
Project-URL: Documentation, https://neuralfit.net/documentation/
Project-URL: Tracker, https://github.com/neural-fit/neuralfit/issues
Platform: UNKNOWN
Requires-Dist: numpy (>=1.14.5)
Provides-Extra: keras
Requires-Dist: tensorflow ; extra == 'keras'
